osrs_ge_scraper/__init__.py
osrs_ge_scraper/api.py
osrs_ge_scraper/item.py
osrs_ge_scraper/utils.py
osrs_ge_scraper-0.1.0.dist-info/METADATA
osrs_ge_scraper-0.1.0.dist-info/WHEEL
osrs_ge_scraper-0.1.0.dist-info/top_level.txt
osrs_ge_scraper-0.1.0.dist-info/RECORD
